obasparql/__init__.py
obasparql/detector.py
obasparql/gquery.py
obasparql/query_manager.py
obasparql/sparqlconnector.py
obasparql/static.py
obasparql/utils.py
obasparql-5.0.3.dist-info/LICENSE
obasparql-5.0.3.dist-info/METADATA
obasparql-5.0.3.dist-info/WHEEL
obasparql-5.0.3.dist-info/top_level.txt
obasparql-5.0.3.dist-info/RECORD
