Metadata-Version: 2.1
Name: obasparql
Version: 5.0.3
Summary: OBA Sparql Manager
Home-page: https://github.com/KnowledgeCaptureAndDiscovery/oba_sparql
Author: Maximiliano Osorio
Author-email: mosorio@isi.edu
License: Apache-2
Classifier: License :: OSI Approved :: Apache Software License
Classifier: Development Status :: 3 - Alpha
Classifier: Programming Language :: Python
Classifier: Programming Language :: Python :: 3
Classifier: Programming Language :: Python :: 3.5
Classifier: Programming Language :: Python :: 3.6
Classifier: Programming Language :: Python :: 3.7
Classifier: Intended Audience :: Science/Research
Classifier: Operating System :: Unix
License-File: LICENSE
Requires-Dist: validators (==0.20.0)
Requires-Dist: pythonql3 (==0.9.83)
Requires-Dist: pyaml (==21.10.1)
Requires-Dist: rdflib (==6.2.0)
Requires-Dist: requests (>=2.20.0)
Requires-Dist: simplejson (==3.17.6)
Requires-Dist: six (>=1.11.0)
Requires-Dist: urllib3 (<1.27,>=1.21.1)
Requires-Dist: webencodings (==0.5.1)
Requires-Dist: starlette (==0.20.4)
Requires-Dist: PyLD (>=2.0.3)
